Metadata-Version: 2.1
Name: Scrap11888
Version: 4.5
Summary: A simple data scraping utility, used to extract data from 11888.gr
Home-page: https://github.com/GeorgeVasiliadis/Scrap11888
Author: George Vasiliadis
Author-email: geor.vasiliadis@gmail.com
License: UNKNOWN
Platform: UNKNOWN
Classifier: Intended Audience :: End Users/Desktop
Classifier: Operating System :: OS Independent
Classifier: Programming Language :: Python :: 3
Classifier: Topic :: Software Development :: User Interfaces
Classifier: Topic :: Utilities
License-File: LICENSE.txt
Requires-Dist: requests
Requires-Dist: openpyxl
